Metadata-Version: 2.1
Name: pcs-to-vmix
Version: 1.0.6
Summary: Interface between Play Cricket Scorer data and vMix & Companion
Home-page: https://gitlab.com/smudge1977/pcs-to-vmix-interface
Author: Keith Marston
Author-email: keith@sneconsulting.co.uk
License: UNKNOWN
Platform: UNKNOWN
